
{"items":[{"name":"Bienvenido"},{"name":"Empezando","href":"getting-started.html","topicHref":"getting-started.html"},{"name":"Instalación","href":"installing.html","topicHref":"installing.html"},{"name":"Soporte AOT Nativo","href":"native-aot.html","topicHref":"native-aot.html"},{"name":"Despliegue","href":"deploying.html","topicHref":"deploying.html"},{"name":"Trabajando con SSL","href":"ssl.html","topicHref":"ssl.html"},{"name":"Configuración en Windows","href":"registering-namespace.html","topicHref":"registering-namespace.html"},{"name":"Registros de cambios","href":"changelogs.html","topicHref":"changelogs.html"},{"name":"Preguntas frecuentes","href":"faq.html","topicHref":"faq.html"},{"name":"Fundamentos"},{"name":"Enrutamiento","href":"fundamentals/routing.html","topicHref":"fundamentals/routing.html"},{"name":"Manejadores de solicitud","href":"fundamentals/request-handlers.html","topicHref":"fundamentals/request-handlers.html"},{"name":"Solicitudes","href":"fundamentals/requests.html","topicHref":"fundamentals/requests.html"},{"name":"Respuestas","href":"fundamentals/responses.html","topicHref":"fundamentals/responses.html"},{"name":"Funcionalidades"},{"name":"Registro de logs","href":"features/logging.html","topicHref":"features/logging.html"},{"name":"Eventos enviados por el servidor","href":"features/server-sent-events.html","topicHref":"features/server-sent-events.html"},{"name":"Web Sockets","href":"features/websockets.html","topicHref":"features/websockets.html"},{"name":"Sintaxis de descarte","href":"features/discard-syntax.html","topicHref":"features/discard-syntax.html"},{"name":"Inyección de dependencias","href":"features/instancing.html","topicHref":"features/instancing.html"},{"name":"Transmisión de contenido","href":"features/content-streaming.html","topicHref":"features/content-streaming.html"},{"name":"Compartición de recursos entre orígenes (CORS)","href":"features/cors.html","topicHref":"features/cors.html"},{"name":"Extensiones"},{"name":"Protocolo de Contexto de Modelo (MCP)","href":"extensions/mcp.html","topicHref":"extensions/mcp.html"},{"name":"JSON-RPC","href":"extensions/json-rpc.html","topicHref":"extensions/json-rpc.html"},{"name":"Proxy SSL","href":"extensions/ssl-proxy.html","topicHref":"extensions/ssl-proxy.html"},{"name":"Autenticación básica","href":"extensions/basic-auth.html","topicHref":"extensions/basic-auth.html"},{"name":"Proveedores de servicios","href":"extensions/service-providers.html","topicHref":"extensions/service-providers.html"},{"name":"Configuración INI","href":"extensions/ini-configuration.html","topicHref":"extensions/ini-configuration.html"},{"name":"Avanzado"},{"name":"Configuración manual","href":"advanced/manual-setup.html","topicHref":"advanced/manual-setup.html"},{"name":"Ciclo de vida de la solicitud","href":"advanced/request-lifecycle.html","topicHref":"advanced/request-lifecycle.html"},{"name":"Resolutores de reenvío","href":"advanced/forwarding-resolvers.html","topicHref":"advanced/forwarding-resolvers.html"},{"name":"Manejadores de servidor HTTP","href":"advanced/http-server-handlers.html","topicHref":"advanced/http-server-handlers.html"},{"name":"Configuración multi-host","href":"advanced/multi-host-setup.html","topicHref":"advanced/multi-host-setup.html"},{"name":"Motores HTTP","href":"advanced/server-engines.html","topicHref":"advanced/server-engines.html"}],"pdf":false}
